SpheroidPy/__init__.py
SpheroidPy-0.0.0.dist-info/METADATA
SpheroidPy-0.0.0.dist-info/WHEEL
SpheroidPy-0.0.0.dist-info/top_level.txt
SpheroidPy-0.0.0.dist-info/RECORD
